{
  "projects": [
    {
      "id": "24411",
      "title": "Two-story 4 bedroom house",
      "subtitle": "Modern contemporary mansion",
      "priceFrom": 270.0,
      "bedrooms": 4,
      "bathrooms": 4,
      "floors": 2,
      "style": "Modern",
      "type": "Residential",
      "sizeSqm": 300,
      "sizeBand": "300-400",
      "heightM": 13.3,
      "widthM": 14.9,
      "images": ["src/images/placeholderImg1.jpg"],
      "badge": "Best Seller",
      "rating": 4.5,
      "reviews": 112,
      "slug": "two-story-4br-24411",
      "featured": true
    },
    {
      "id": "13418",
      "title": "Contemporary 3 bedroom house",
      "subtitle": "Family home",
      "priceFrom": 181.8,
      "bedrooms": 3,
      "bathrooms": 2,
      "floors": 1,
      "style": "Contemporary",
      "type": "Residential",
      "sizeSqm": 180,
      "sizeBand": "100-200",
      "heightM": 15,
      "widthM": 17,
      "images": ["src/images/placeholderImg2.jpg"],
      "badge": "Best Seller",
      "rating": 4.0,
      "reviews": 87,
      "slug": "contemporary-3br-13418",
      "featured": true
    },
    {
      "id": "38901",
      "title": "8 bedroom Modern contemporary mansion",
      "subtitle": "Luxury residence",
      "priceFrom": 1961.2,
      "bedrooms": 8,
      "bathrooms": 10,
      "floors": 3,
      "style": "Modern",
      "type": "Residential",
      "sizeSqm": 1068,
      "sizeBand": "750-plus",
      "heightM": 17,
      "widthM": 32,
      "images": ["src/images/placeholderImg1.jpg"],
      "badge": "Best Seller",
      "rating": 5.0,
      "reviews": 45,
      "slug": "8br-modern-mansion-38901",
      "featured": true
    },
    {
      "id": "p-1br",
      "title": "1 Bedroom House Plan",
      "priceFrom": 95.0,
      "bedrooms": 1,
      "bathrooms": 1,
      "floors": 1,
      "style": "Bungalow",
      "type": "Residential",
      "sizeSqm": 65,
      "sizeBand": "under-100",
      "heightM": 8,
      "widthM": 10,
      "images": ["src/images/placeholderImg1.jpg"],
      "rating": 4.2,
      "reviews": 22,
      "slug": "1br-plan"
    },
    {
      "id": "p-2br",
      "title": "2 Bedroom House Plan",
      "priceFrom": 140.0,
      "bedrooms": 2,
      "bathrooms": 1,
      "floors": 1,
      "style": "Country",
      "type": "Residential",
      "sizeSqm": 120,
      "sizeBand": "100-200",
      "heightM": 10,
      "widthM": 12,
      "images": ["src/images/placeholderImg1.jpg"],
      "rating": 4.3,
      "reviews": 34,
      "slug": "2br-plan"
    },
    {
      "id": "p-hotel-01",
      "title": "Boutique Lodge",
      "priceFrom": 480.0,
      "bedrooms": 20,
      "bathrooms": 15,
      "floors": 2,
      "style": "Luxury",
      "type": "Hotels & Lodges",
      "sizeSqm": 900,
      "sizeBand": "750-plus",
      "heightM": 25,
      "widthM": 40,
      "images": ["src/images/placeholderImg2.jpg"],
      "rating": 4.6,
      "reviews": 12,
      "slug": "boutique-lodge"
    },
    {
      "id": "56021",
      "title": "Luxury 5 bedroom villa",
      "subtitle": "Premium estate",
      "priceFrom": 680.5,
      "bedrooms": 5,
      "bathrooms": 6,
      "floors": 2,
      "style": "Luxury",
      "type": "Residential",
      "sizeSqm": 540,
      "sizeBand": "500-750",
      "heightM": 15,
      "widthM": 25,
      "images": ["src/images/placeholderImg2.jpg"],
      "badge": "Best Seller",
      "rating": 5.0,
      "reviews": 28,
      "slug": "luxury-5br-villa-56021",
      "featured": false
    },
    {
      "id": "77702",
      "title": "Cozy 2 bedroom cottage",
      "subtitle": "Country retreat",
      "priceFrom": 120.0,
      "bedrooms": 2,
      "bathrooms": 1,
      "floors": 1,
      "style": "Rustic",
      "type": "Residential",
      "sizeSqm": 110,
      "sizeBand": "100-200",
      "heightM": 6,
      "widthM": 10,
      "images": ["src/images/placeholderImg1.jpg"],
      "badge": "Best Seller",
      "rating": 3.0,
      "reviews": 15,
      "slug": "cozy-2br-cottage-77702",
      "featured": false
    }
  ]
}
